
{
  "header": {
    "reportVersion": 1,
    "event": "Allocation failed - JavaScript heap out of memory",
    "trigger": "FatalError",
    "filename": "report.20200331.080933.5498.0.001.json",
    "dumpEventTime": "2020-03-31T08:09:33Z",
    "dumpEventTimeStamp": "1585652973964",
    "processId": 5498,
    "cwd": "/home/eduardo/PhpStormProjects/supp-core/supp-administrativo-frontend",
    "commandLine": [
      "/home/eduardo/PhpStormProjects/supp-core/supp-administrativo-frontend/node_modules/node/bin/node",
      "/home/eduardo/PhpStormProjects/supp-core/supp-administrativo-frontend/node_modules/.bin/ngcc"
    ],
    "nodejsVersion": "v12.16.1",
    "glibcVersionRuntime": "2.30",
    "glibcVersionCompiler": "2.17",
    "wordSize": 64,
    "arch": "x64",
    "platform": "linux",
    "componentVersions": {
      "node": "12.16.1",
      "v8": "7.8.279.23-node.31",
      "uv": "1.34.0",
      "zlib": "1.2.11",
      "brotli": "1.0.7",
      "ares": "1.15.0",
      "modules": "72",
      "nghttp2": "1.40.0",
      "napi": "5",
      "llhttp": "2.0.4",
      "http_parser": "2.9.3",
      "openssl": "1.1.1d",
      "cldr": "35.1",
      "icu": "64.2",
      "tz": "2019c",
      "unicode": "12.1"
    },
    "release": {
      "name": "node",
      "lts": "Erbium",
      "headersUrl": "https://nodejs.org/download/release/v12.16.1/node-v12.16.1-headers.tar.gz",
      "sourceUrl": "https://nodejs.org/download/release/v12.16.1/node-v12.16.1.tar.gz"
    },
    "osName": "Linux",
    "osRelease": "5.3.0-42-generic",
    "osVersion": "#34-Ubuntu SMP Fri Feb 28 05:49:40 UTC 2020",
    "osMachine": "x86_64",
    "cpus": [
      {
        "model": "Intel(R) Core(TM) i7-8550U CPU @ 1.80GHz",
        "speed": 1799,
        "user": 38438400,
        "nice": 969000,
        "sys": 6386600,
        "idle": 226543200,
        "irq": 0
      },
      {
        "model": "Intel(R) Core(TM) i7-8550U CPU @ 1.80GHz",
        "speed": 1800,
        "user": 38547000,
        "nice": 975700,
        "sys": 5649900,
        "idle": 8157600,
        "irq": 0
      },
      {
        "model": "Intel(R) Core(TM) i7-8550U CPU @ 1.80GHz",
        "speed": 1799,
        "user": 39080000,
        "nice": 1056300,
        "sys": 5654200,
        "idle": 8093300,
        "irq": 0
      },
      {
        "model": "Intel(R) Core(TM) i7-8550U CPU @ 1.80GHz",
        "speed": 1800,
        "user": 39383000,
        "nice": 1042800,
        "sys": 5774600,
        "idle": 8211000,
        "irq": 0
      },
      {
        "model": "Intel(R) Core(TM) i7-8550U CPU @ 1.80GHz",
        "speed": 1788,
        "user": 38697200,
        "nice": 943700,
        "sys": 5923700,
        "idle": 7680200,
        "irq": 0
      },
      {
        "model": "Intel(R) Core(TM) i7-8550U CPU @ 1.80GHz",
        "speed": 1800,
        "user": 37719700,
        "nice": 998000,
        "sys": 6863300,
        "idle": 8045000,
        "irq": 0
      },
      {
        "model": "Intel(R) Core(TM) i7-8550U CPU @ 1.80GHz",
        "speed": 1777,
        "user": 38290600,
        "nice": 905200,
        "sys": 8080000,
        "idle": 8002500,
        "irq": 0
      },
      {
        "model": "Intel(R) Core(TM) i7-8550U CPU @ 1.80GHz",
        "speed": 1800,
        "user": 38376800,
        "nice": 945600,
        "sys": 5923600,
        "idle": 8014900,
        "irq": 0
      }
    ],
    "networkInterfaces": [
      {
        "name": "lo",
        "internal": true,
        "mac": "00:00:00:00:00:00",
        "address": "127.0.0.1",
        "netmask": "255.0.0.0",
        "family": "IPv4"
      },
      {
        "name": "wlp3s0",
        "internal": false,
        "mac": "90:32:4b:98:ea:3d",
        "address": "192.168.1.111",
        "netmask": "255.255.255.0",
        "family": "IPv4"
      },
      {
        "name": "br-3e8088c02c19",
        "internal": false,
        "mac": "02:42:f5:07:54:1b",
        "address": "192.168.0.1",
        "netmask": "255.255.255.0",
        "family": "IPv4"
      },
      {
        "name": "tun0",
        "internal": false,
        "mac": "00:00:00:00:00:00",
        "address": "172.29.1.217",
        "netmask": "255.255.255.255",
        "family": "IPv4"
      },
      {
        "name": "lo",
        "internal": true,
        "mac": "00:00:00:00:00:00",
        "address": "::1",
        "netmask": "ffff:ffff:ffff:ffff:ffff:ffff:ffff:ffff",
        "family": "IPv6",
        "scopeid": 0
      },
      {
        "name": "wlp3s0",
        "internal": false,
        "mac": "90:32:4b:98:ea:3d",
        "address": "fe80::e12a:d14d:4d95:8558",
        "netmask": "ffff:ffff:ffff:ffff::",
        "family": "IPv6",
        "scopeid": 3
      },
      {
        "name": "br-3e8088c02c19",
        "internal": false,
        "mac": "02:42:f5:07:54:1b",
        "address": "fe80::42:f5ff:fe07:541b",
        "netmask": "ffff:ffff:ffff:ffff::",
        "family": "IPv6",
        "scopeid": 43
      },
      {
        "name": "veth7544194",
        "internal": false,
        "mac": "52:42:71:62:94:c5",
        "address": "fe80::5042:71ff:fe62:94c5",
        "netmask": "ffff:ffff:ffff:ffff::",
        "family": "IPv6",
        "scopeid": 45
      },
      {
        "name": "veth68ff5b6",
        "internal": false,
        "mac": "36:6d:39:bf:e2:f3",
        "address": "fe80::346d:39ff:febf:e2f3",
        "netmask": "ffff:ffff:ffff:ffff::",
        "family": "IPv6",
        "scopeid": 47
      },
      {
        "name": "veth9b170ac",
        "internal": false,
        "mac": "22:e4:f7:50:6d:5a",
        "address": "fe80::20e4:f7ff:fe50:6d5a",
        "netmask": "ffff:ffff:ffff:ffff::",
        "family": "IPv6",
        "scopeid": 49
      },
      {
        "name": "veth34ca633",
        "internal": false,
        "mac": "92:3d:90:3a:48:46",
        "address": "fe80::903d:90ff:fe3a:4846",
        "netmask": "ffff:ffff:ffff:ffff::",
        "family": "IPv6",
        "scopeid": 51
      },
      {
        "name": "veth9132bec",
        "internal": false,
        "mac": "5a:2d:c8:cf:0a:46",
        "address": "fe80::582d:c8ff:fecf:a46",
        "netmask": "ffff:ffff:ffff:ffff::",
        "family": "IPv6",
        "scopeid": 53
      },
      {
        "name": "veth2240fe3",
        "internal": false,
        "mac": "62:5a:74:06:6a:79",
        "address": "fe80::605a:74ff:fe06:6a79",
        "netmask": "ffff:ffff:ffff:ffff::",
        "family": "IPv6",
        "scopeid": 55
      },
      {
        "name": "vethb60280a",
        "internal": false,
        "mac": "2e:d2:73:34:8c:d1",
        "address": "fe80::2cd2:73ff:fe34:8cd1",
        "netmask": "ffff:ffff:ffff:ffff::",
        "family": "IPv6",
        "scopeid": 57
      },
      {
        "name": "veth400411d",
        "internal": false,
        "mac": "1e:1f:c4:1c:c9:21",
        "address": "fe80::1c1f:c4ff:fe1c:c921",
        "netmask": "ffff:ffff:ffff:ffff::",
        "family": "IPv6",
        "scopeid": 61
      },
      {
        "name": "tun0",
        "internal": false,
        "mac": "00:00:00:00:00:00",
        "address": "fe80::8df3:43aa:b696:626c",
        "netmask": "ffff:ffff:ffff:ffff::",
        "family": "IPv6",
        "scopeid": 62
      }
    ],
    "host": "note-edu"
  },
  "javascriptStack": {
    "message": "No stack.",
    "stack": [
      "Unavailable."
    ]
  },
  "nativeStack": [
    {
      "pc": "0x0000000000b278f5",
      "symbol": "report::TriggerNodeReport(v8::Isolate*, node::Environment*, char const*, char const*, std::string const&, v8::Local<v8::String>) [/home/eduardo/PhpStormProjects/supp-core/supp-administrativo-frontend/node_modules/node/bin/node]"
    },
    {
      "pc": "0x00000000009f13ec",
      "symbol": "node::OnFatalError(char const*, char const*) [/home/eduardo/PhpStormProjects/supp-core/supp-administrativo-frontend/node_modules/node/bin/node]"
    },
    {
      "pc": "0x0000000000b5da9e",
      "symbol": "v8::Utils::ReportOOMFailure(v8::internal::Isolate*, char const*, bool) [/home/eduardo/PhpStormProjects/supp-core/supp-administrativo-frontend/node_modules/node/bin/node]"
    },
    {
      "pc": "0x0000000000b5de19",
      "symbol": "v8::internal::V8::FatalProcessOutOfMemory(v8::internal::Isolate*, char const*, bool) [/home/eduardo/PhpStormProjects/supp-core/supp-administrativo-frontend/node_modules/node/bin/node]"
    },
    {
      "pc": "0x0000000000d0a765",
      "symbol": " [/home/eduardo/PhpStormProjects/supp-core/supp-administrativo-frontend/node_modules/node/bin/node]"
    },
    {
      "pc": "0x0000000000d0adf6",
      "symbol": "v8::internal::Heap::RecomputeLimits(v8::internal::GarbageCollector) [/home/eduardo/PhpStormProjects/supp-core/supp-administrativo-frontend/node_modules/node/bin/node]"
    },
    {
      "pc": "0x0000000000d1760a",
      "symbol": "v8::internal::Heap::PerformGarbageCollection(v8::internal::GarbageCollector, v8::GCCallbackFlags) [/home/eduardo/PhpStormProjects/supp-core/supp-administrativo-frontend/node_modules/node/bin/node]"
    },
    {
      "pc": "0x0000000000d18515",
      "symbol": "v8::internal::Heap::CollectGarbage(v8::internal::AllocationSpace, v8::internal::GarbageCollectionReason, v8::GCCallbackFlags) [/home/eduardo/PhpStormProjects/supp-core/supp-administrativo-frontend/node_modules/node/bin/node]"
    },
    {
      "pc": "0x0000000000d1afcc",
      "symbol": "v8::internal::Heap::AllocateRawWithRetryOrFail(int, v8::internal::AllocationType, v8::internal::AllocationOrigin, v8::internal::AllocationAlignment) [/home/eduardo/PhpStormProjects/supp-core/supp-administrativo-frontend/node_modules/node/bin/node]"
    },
    {
      "pc": "0x0000000000ce19bb",
      "symbol": "v8::internal::Factory::NewFillerObject(int, bool, v8::internal::AllocationType, v8::internal::AllocationOrigin) [/home/eduardo/PhpStormProjects/supp-core/supp-administrativo-frontend/node_modules/node/bin/node]"
    },
    {
      "pc": "0x000000000102482c",
      "symbol": "v8::internal::Runtime_AllocateInOldGeneration(int, unsigned long*, v8::internal::Isolate*) [/home/eduardo/PhpStormProjects/supp-core/supp-administrativo-frontend/node_modules/node/bin/node]"
    },
    {
      "pc": "0x00000000013a71b9",
      "symbol": " [/home/eduardo/PhpStormProjects/supp-core/supp-administrativo-frontend/node_modules/node/bin/node]"
    }
  ],
  "javascriptHeap": {
    "totalMemory": 2155294720,
    "totalCommittedMemory": 2150954328,
    "usedMemory": 2146464520,
    "availableMemory": 47248056,
    "memoryLimit": 2197815296,
    "heapSpaces": {
      "read_only_space": {
        "memorySize": 262144,
        "committedMemory": 33088,
        "capacity": 32808,
        "used": 32808,
        "available": 0
      },
      "new_space": {
        "memorySize": 4194304,
        "committedMemory": 662848,
        "capacity": 2094912,
        "used": 162960,
        "available": 1931952
      },
      "old_space": {
        "memorySize": 2090221568,
        "committedMemory": 2089876960,
        "capacity": 2087253544,
        "used": 2086552928,
        "available": 700616
      },
      "code_space": {
        "memorySize": 2265088,
        "committedMemory": 2033568,
        "capacity": 1899360,
        "used": 1899360,
        "available": 0
      },
      "map_space": {
        "memorySize": 1052672,
        "committedMemory": 1048920,
        "capacity": 762320,
        "used": 762320,
        "available": 0
      },
      "large_object_space": {
        "memorySize": 57249792,
        "committedMemory": 57249792,
        "capacity": 57051360,
        "used": 57051360,
        "available": 0
      },
      "code_large_object_space": {
        "memorySize": 49152,
        "committedMemory": 49152,
        "capacity": 2784,
        "used": 2784,
        "available": 0
      },
      "new_large_object_space": {
        "memorySize": 0,
        "committedMemory": 0,
        "capacity": 2094912,
        "used": 0,
        "available": 2094912
      }
    }
  },
  "resourceUsage": {
    "userCpuSeconds": 270.491,
    "kernelCpuSeconds": 8.37086,
    "cpuConsumptionPercent": 103.282,
    "maxRss": 2257022976,
    "pageFaults": {
      "IORequired": 11,
      "IONotRequired": 1123529
    },
    "fsActivity": {
      "reads": 24952,
      "writes": 23008
    }
  },
  "uvthreadResourceUsage": {
    "userCpuSeconds": 168.226,
    "kernelCpuSeconds": 5.13763,
    "cpuConsumptionPercent": 64.2089,
    "fsActivity": {
      "reads": 24952,
      "writes": 23008
    }
  },
  "libuv": [
  ],
  "environmentVariables": {
    "GJS_DEBUG_TOPICS": "JS ERROR;JS LOG",
    "LESSOPEN": "| /usr/bin/lesspipe %s",
    "npm_package_scripts_bundle_report": "webpack-bundle-analyzer dist/stats.json",
    "npm_package_dependencies__swimlane_ngx_charts": "13.0.2",
    "npm_package_devDependencies__angular_language_service": "9.1.0",
    "npm_package_devDependencies__types_node": "12.12.29",
    "npm_package_devDependencies_ts_node": "7.0.1",
    "npm_package_devDependencies_tslint": "5.20.1",
    "npm_config_cache_lock_stale": "60000",
    "npm_config_ham_it_up": "",
    "npm_package_dependencies__angular_animations": "9.1.0",
    "npm_config_legacy_bundling": "",
    "npm_config_sign_git_tag": "",
    "LANGUAGE": "en_US:",
    "J2SDKDIR": "/usr/lib/jvm/java-8-oracle",
    "USER": "eduardo",
    "LC_TIME": "pt_BR.UTF-8",
    "npm_package_dependencies_node_sass": "4.13.1",
    "npm_package_devDependencies_karma_coverage_istanbul_reporter": "2.1.1",
    "npm_package_devDependencies_webpack_bundle_analyzer": "3.6.1",
    "npm_config_user_agent": "npm/6.14.4 node/v10.15.3 linux x64",
    "npm_config_always_auth": "",
    "npm_package_dependencies__ngrx_store": "9.0.0",
    "npm_package_dependencies__ngrx_store_devtools": "9.0.0",
    "npm_config_bin_links": "true",
    "npm_config_key": "",
    "SSH_AGENT_PID": "2476",
    "XDG_SESSION_TYPE": "x11",
    "npm_package_dependencies__angular_common": "9.1.0",
    "npm_package_dependencies_angular_in_memory_web_api": "0.10.0",
    "npm_config_allow_same_version": "",
    "npm_config_description": "true",
    "npm_config_fetch_retries": "2",
    "npm_config_heading": "npm",
    "npm_config_if_present": "",
    "npm_config_init_version": "1.0.0",
    "npm_config_user": "1001",
    "npm_node_execpath": "/home/eduardo/.nvm/versions/node/v10.15.3/bin/node",
    "J2REDIR": "/usr/lib/jvm/java-8-oracle/jre",
    "SENCHA_CMD_3_0_0": "/home/eduardo/bin/Sencha/Cmd/4.0.4.84",
    "SHLVL": "1",
    "npm_package_scripts_build_prod_stats": "node --max_old_space_size=6144 ./node_modules/@angular/cli/bin/ng build --prod --stats-json",
    "npm_package_dependencies__angular_flex_layout": "9.0.0-beta.29",
    "npm_package_dependencies_html_webpack_plugin": "3.2.0",
    "npm_package_dependencies_rxjs": "6.5.4",
    "npm_package_devDependencies__types_jasminewd2": "2.0.8",
    "npm_package_devDependencies_protractor": "6.0.0",
    "npm_config_prefer_online": "",
    "npm_config_noproxy": "",
    "QT4_IM_MODULE": "ibus",
    "HOME": "/home/eduardo",
    "OLDPWD": "/home/eduardo/PhpStormProjects/supp-core",
    "npm_package_dependencies_chart_js": "2.9.3",
    "npm_config_force": "",
    "DESKTOP_SESSION": "ubuntu",
    "NVM_BIN": "/home/eduardo/.nvm/versions/node/v10.15.3/bin",
    "npm_package_dependencies__angular_material": "9.2.0",
    "npm_package_dependencies__ngx_translate_core": "12.1.2",
    "npm_config_only": "",
    "npm_config_read_only": "",
    "npm_package_dependencies_angular_calendar": "0.28.5",
    "npm_package_devDependencies_jasmine_core": "3.5.0",
    "npm_config_cache_min": "10",
    "npm_config_init_license": "ISC",
    "GNOME_SHELL_SESSION_MODE": "ubuntu",
    "GTK_MODULES": "gail:atk-bridge",
    "npm_package_dependencies_angular_resizable_element": "3.3.0",
    "npm_package_devDependencies__types_jasmine": "3.5.7",
    "npm_config_editor": "vi",
    "npm_config_rollback": "true",
    "npm_config_tag_version_prefix": "v",
    "LC_MONETARY": "pt_BR.UTF-8",
    "MANAGERPID": "2344",
    "LC_CTYPE": "pt_BR.UTF-8",
    "npm_package_dependencies_reflect_metadata": "0.1.13",
    "npm_package_devDependencies_karma": "4.4.1",
    "npm_config_cache_max": "Infinity",
    "npm_config_timing": "",
    "npm_config_userconfig": "/home/eduardo/.npmrc",
    "DBUS_SESSION_BUS_ADDRESS": "unix:path=/run/user/1001/bus",
    "npm_package_scripts_postinstall": "ngcc",
    "npm_package_dependencies_moment": "2.24.0",
    "npm_package_dependencies_node": "12.16.1",
    "npm_package_devDependencies__angular_compiler_cli": "9.1.0",
    "npm_package_devDependencies_karma_chrome_launcher": "2.2.0",
    "npm_config_engine_strict": "",
    "npm_config_init_author_name": "",
    "npm_config_init_author_url": "",
    "npm_config_preid": "",
    "npm_config_tmp": "/tmp",
    "COLORTERM": "truecolor",
    "npm_package_scripts_start_hmr": "ng serve --configuration hmr --source-map=false --hmr-warning=false",
    "npm_package_dependencies__angular_cdk": "9.2.0",
    "npm_package_devDependencies_typescript": "3.8.3",
    "npm_package_description": "leia",
    "npm_config_depth": "Infinity",
    "npm_config_package_lock_only": "",
    "npm_config_save_dev": "",
    "npm_config_usage": "",
    "NVM_DIR": "/home/eduardo/.nvm",
    "npm_package_dependencies_d3": "5.15.0",
    "npm_package_devDependencies_jasmine_spec_reporter": "4.2.1",
    "npm_package_readmeFilename": "README.md",
    "npm_config_metrics_registry": "https://registry.npmjs.org/",
    "npm_config_cafile": "",
    "npm_config_otp": "",
    "npm_config_package_lock": "true",
    "npm_config_progress": "true",
    "npm_config_https_proxy": "",
    "npm_config_save_prod": "",
    "MANDATORY_PATH": "/usr/share/gconf/ubuntu.mandatory.path",
    "QT_QPA_PLATFORMTHEME": "appmenu-qt5",
    "IM_CONFIG_PHASE": "1",
    "npm_package_scripts_build_prod": "node --max_old_space_size=6144 ./node_modules/@angular/cli/bin/ng build --prod",
    "npm_package_dependencies__angular_core": "9.1.0",
    "npm_package_dependencies__swimlane_dragula": "3.8.0",
    "npm_package_dependencies_prismjs": "1.19.0",
    "npm_config_audit": "true",
    "npm_config_cidr": "",
    "npm_config_onload_script": "",
    "npm_config_sso_type": "oauth",
    "GTK_IM_MODULE": "ibus",
    "LOGNAME": "eduardo",
    "npm_package_dependencies_hammerjs": "2.0.8",
    "npm_config_rebuild_bundle": "true",
    "npm_config_save_bundle": "",
    "npm_config_shell": "/bin/bash",
    "JOURNAL_STREAM": "9:54460",
    "_": "/home/eduardo/.nvm/versions/node/v10.15.3/bin/npm",
    "npm_package_private": "true",
    "npm_package_dependencies__angular_platform_browser_dynamic": "9.1.0",
    "npm_config_dry_run": "",
    "npm_config_format_package_lock": "true",
    "npm_config_prefix": "/home/eduardo/.nvm/versions/node/v10.15.3",
    "XDG_SESSION_CLASS": "user",
    "DEFAULTS_PATH": "/usr/share/gconf/ubuntu.default.path",
    "npm_package_scripts_lint": "ng lint",
    "npm_package_dependencies_class_transformer": "0.2.3",
    "npm_package_dependencies_ngx_cookie_service": "2.3.0",
    "npm_config_scope": "",
    "npm_config_browser": "",
    "npm_config_cache_lock_wait": "10000",
    "npm_config_ignore_prepublish": "",
    "npm_config_registry": "https://registry.npmjs.org/",
    "npm_config_save_optional": "",
    "npm_config_searchopts": "",
    "npm_config_versions": "",
    "USERNAME": "eduardo",
    "TERM": "xterm-256color",
    "npm_package_dependencies_core_js": "3.6.4",
    "npm_package_devDependencies__types_lodash": "4.14.149",
    "npm_package_devDependencies_karma_jasmine_html_reporter": "1.5.2",
    "npm_config_cache": "/home/eduardo/.npm",
    "npm_config_proxy": "",
    "npm_config_send_metrics": "",
    "GNOME_DESKTOP_SESSION_ID": "this-is-deprecated",
    "npm_package_scripts_start": "ng serve --open",
    "npm_package_scripts_build_stats": "node --max_old_space_size=6144 ./node_modules/@angular/cli/bin/ng build --dev --stats-json",
    "npm_package_dependencies__angular_compiler": "9.1.0",
    "npm_config_global_style": "",
    "npm_config_ignore_scripts": "",
    "npm_config_version": "",
    "GTK2_MODULES": "overlay-scrollbar",
    "WINDOWPATH": "2",
    "npm_package_dependencies_ng2_ckeditor": "1.2.7",
    "npm_package_dependencies_ngrx_store_freeze": "0.2.4",
    "npm_config_local_address": "",
    "npm_config_viewer": "man",
    "npm_config_node_gyp": "/home/eduardo/.nvm/versions/node/v10.15.3/lib/node_modules/npm/node_modules/node-gyp/bin/node-gyp.js",
    "PATH": "/home/eduardo/.nvm/versions/node/v10.15.3/lib/node_modules/npm/node_modules/npm-lifecycle/node-gyp-bin:/home/eduardo/PhpStormProjects/supp-core/supp-administrativo-frontend/node_modules/.bin:/home/eduardo/bin/Sencha/Cmd/4.0.4.84:/home/eduardo/.nvm/versions/node/v10.15.3/bin:/home/eduardo/bin/Sencha/Cmd/4.0.4.84:/home/eduardo/bin:/usr/local/sbin:/usr/local/bin:/usr/sbin:/usr/bin:/sbin:/bin:/usr/games:/usr/local/games:/snap/bin:/usr/lib/jvm/java-8-oracle/bin:/usr/lib/jvm/java-8-oracle/db/bin:/usr/lib/jvm/java-8-oracle/jre/bin",
    "SESSION_MANAGER": "local/note-edu:@/tmp/.ICE-unix/2516,unix/note-edu:/tmp/.ICE-unix/2516",
    "DERBY_HOME": "/usr/lib/jvm/java-8-oracle/db",
    "INVOCATION_ID": "6ac4dd4225784609be0bfa1bc043bd8b",
    "npm_package_name": "supp-administrativo-frontend",
    "npm_package_dependencies_css_element_queries": "1.2.3",
    "npm_config_audit_level": "low",
    "npm_config_prefer_offline": "",
    "NODE": "/home/eduardo/.nvm/versions/node/v10.15.3/bin/node",
    "XDG_MENU_PREFIX": "gnome-",
    "LC_ADDRESS": "pt_BR.UTF-8",
    "GNOME_TERMINAL_SCREEN": "/org/gnome/Terminal/screen/e5218222_8a7f_4e12_8bb7_da52a3e20ba5",
    "XDG_RUNTIME_DIR": "/run/user/1001",
    "npm_package_dependencies_ngx_infinite_scroll": "8.0.1",
    "npm_package_devDependencies__phenomnomnominal_angular_lazy_routes_fix": "0.1.5",
    "npm_config_color": "true",
    "npm_config_sign_git_commit": "",
    "DISPLAY": ":0",
    "npm_package_dependencies__angular_forms": "9.1.0",
    "npm_package_dependencies_angular": "1.7.9",
    "npm_config_fetch_retry_mintimeout": "10000",
    "npm_config_maxsockets": "50",
    "npm_config_offline": "",
    "npm_config_sso_poll_frequency": "500",
    "LANG": "en_US.UTF-8",
    "XDG_CURRENT_DESKTOP": "ubuntu:GNOME",
    "LC_TELEPHONE": "pt_BR.UTF-8",
    "npm_package_dependencies_event_source_polyfill": "1.0.12",
    "npm_config_umask": "0022",
    "XMODIFIERS": "@im=ibus",
    "XDG_SESSION_DESKTOP": "ubuntu",
    "XAUTHORITY": "/run/user/1001/gdm/Xauthority",
    "DESKTOP_MODE": "1",
    "LS_COLORS": "rs=0:di=01;34:ln=01;36:mh=00:pi=40;33:so=01;35:do=01;35:bd=40;33;01:cd=40;33;01:or=40;31;01:mi=00:su=37;41:sg=30;43:ca=30;41:tw=30;42:ow=34;42:st=37;44:ex=01;32:*.tar=01;31:*.tgz=01;31:*.arc=01;31:*.arj=01;31:*.taz=01;31:*.lha=01;31:*.lz4=01;31:*.lzh=01;31:*.lzma=01;31:*.tlz=01;31:*.txz=01;31:*.tzo=01;31:*.t7z=01;31:*.zip=01;31:*.z=01;31:*.dz=01;31:*.gz=01;31:*.lrz=01;31:*.lz=01;31:*.lzo=01;31:*.xz=01;31:*.zst=01;31:*.tzst=01;31:*.bz2=01;31:*.bz=01;31:*.tbz=01;31:*.tbz2=01;31:*.tz=01;31:*.deb=01;31:*.rpm=01;31:*.jar=01;31:*.war=01;31:*.ear=01;31:*.sar=01;31:*.rar=01;31:*.alz=01;31:*.ace=01;31:*.zoo=01;31:*.cpio=01;31:*.7z=01;31:*.rz=01;31:*.cab=01;31:*.wim=01;31:*.swm=01;31:*.dwm=01;31:*.esd=01;31:*.jpg=01;35:*.jpeg=01;35:*.mjpg=01;35:*.mjpeg=01;35:*.gif=01;35:*.bmp=01;35:*.pbm=01;35:*.pgm=01;35:*.ppm=01;35:*.tga=01;35:*.xbm=01;35:*.xpm=01;35:*.tif=01;35:*.tiff=01;35:*.png=01;35:*.svg=01;35:*.svgz=01;35:*.mng=01;35:*.pcx=01;35:*.mov=01;35:*.mpg=01;35:*.mpeg=01;35:*.m2v=01;35:*.mkv=01;35:*.webm=01;35:*.ogm=01;35:*.mp4=01;35:*.m4v=01;35:*.mp4v=01;35:*.vob=01;35:*.qt=01;35:*.nuv=01;35:*.wmv=01;35:*.asf=01;35:*.rm=01;35:*.rmvb=01;35:*.flc=01;35:*.avi=01;35:*.fli=01;35:*.flv=01;35:*.gl=01;35:*.dl=01;35:*.xcf=01;35:*.xwd=01;35:*.yuv=01;35:*.cgm=01;35:*.emf=01;35:*.ogv=01;35:*.ogx=01;35:*.aac=00;36:*.au=00;36:*.flac=00;36:*.m4a=00;36:*.mid=00;36:*.midi=00;36:*.mka=00;36:*.mp3=00;36:*.mpc=00;36:*.ogg=00;36:*.ra=00;36:*.wav=00;36:*.oga=00;36:*.opus=00;36:*.spx=00;36:*.xspf=00;36:",
    "GNOME_TERMINAL_SERVICE": ":1.90",
    "npm_package_scripts_ng": "ng",
    "npm_package_scripts_e2e": "ng e2e",
    "npm_package_dependencies_classlist_js": "1.1.20150312",
    "npm_package_gitHead": "c25ecf7f2d2d63ced35b22a954cf926ea5d88915",
    "npm_config_fund": "true",
    "npm_config_fetch_retry_maxtimeout": "60000",
    "npm_config_loglevel": "notice",
    "npm_config_logs_max": "10",
    "npm_config_message": "%s",
    "npm_lifecycle_script": "ngcc",
    "SSH_AUTH_SOCK": "/run/user/1001/keyring/ssh",
    "npm_package_scripts_test": "ng test",
    "npm_package_dependencies__ngrx_effects": "9.0.0",
    "npm_package_dependencies_material_community_components": "6.0.0",
    "npm_config_ca": "",
    "npm_config_cert": "",
    "npm_config_global": "",
    "npm_config_link": "",
    "SHELL": "/bin/bash",
    "LC_NAME": "pt_BR.UTF-8",
    "npm_package_version": "0.0.1",
    "npm_package_scripts_start_hmr_sourcemaps": "ng serve --configuration hmr --source-map=true --hmr-warning=false",
    "npm_package_dependencies_ngx_drag_drop": "2.0.0",
    "npm_config_access": "",
    "npm_config_also": "",
    "npm_config_save": "true",
    "npm_config_unicode": "true",
    "npm_lifecycle_event": "postinstall",
    "GDMSESSION": "ubuntu",
    "npm_package_scripts_build": "node --max_old_space_size=6144 ./node_modules/@angular/cli/bin/ng build --dev",
    "npm_package_dependencies__angular_router": "9.1.0",
    "npm_package_dependencies__types_prismjs": "1.16.0",
    "npm_package_dependencies_ngx_upper_case_directive": "1.0.3",
    "npm_package_dependencies_perfect_scrollbar": "1.5.0",
    "npm_package_dependencies_web_animations_js": "2.3.2",
    "npm_package_devDependencies_tslib": "1.11.1",
    "npm_config_argv": "{\"remain\":[],\"cooked\":[\"install\"],\"original\":[\"install\"]}",
    "npm_config_before": "",
    "npm_config_long": "",
    "npm_config_production": "",
    "npm_config_searchlimit": "20",
    "npm_config_unsafe_perm": "true",
    "npm_config_update_notifier": "true",
    "LESSCLOSE": "/usr/bin/lesspipe %s %s",
    "npm_package_dependencies_fibers": "4.0.2",
    "npm_package_dependencies_lodash": "4.17.15",
    "npm_package_devDependencies_karma_jasmine": "2.0.1",
    "npm_config_auth_type": "legacy",
    "npm_config_node_version": "10.15.3",
    "npm_config_tag": "latest",
    "LC_MEASUREMENT": "pt_BR.UTF-8",
    "npm_package_dependencies__angular_material_moment_adapter": "9.2.0",
    "npm_package_dependencies__ngrx_router_store": "9.0.0",
    "npm_config_git_tag_version": "true",
    "npm_config_commit_hooks": "true",
    "npm_config_script_shell": "",
    "npm_config_shrinkwrap": "true",
    "GPG_AGENT_INFO": "/run/user/1001/gnupg/S.gpg-agent:0:1",
    "GJS_DEBUG_OUTPUT": "stderr",
    "LC_IDENTIFICATION": "pt_BR.UTF-8",
    "npm_package_license": "https://www.agu.gov.br",
    "npm_config_fetch_retry_factor": "10",
    "npm_config_save_exact": "",
    "npm_config_strict_ssl": "true",
    "QT_IM_MODULE": "ibus",
    "npm_package_devDependencies__angular_cli": "9.1.0",
    "npm_config_dev": "",
    "npm_config_globalconfig": "/home/eduardo/.nvm/versions/node/v10.15.3/etc/npmrc",
    "npm_config_init_module": "/home/eduardo/.npm-init.js",
    "npm_config_parseable": "",
    "JAVA_HOME": "/usr/lib/jvm/java-8-oracle",
    "PWD": "/home/eduardo/PhpStormProjects/supp-core/supp-administrativo-frontend",
    "npm_config_globalignorefile": "/home/eduardo/.nvm/versions/node/v10.15.3/etc/npmignore",
    "npm_execpath": "/home/eduardo/.nvm/versions/node/v10.15.3/lib/node_modules/npm/bin/npm-cli.js",
    "XDG_CONFIG_DIRS": "/etc/xdg/xdg-ubuntu:/etc/xdg",
    "CLUTTER_IM_MODULE": "ibus",
    "NVM_CD_FLAGS": "",
    "XDG_DATA_DIRS": "/usr/share/ubuntu:/usr/local/share/:/usr/share/:/var/lib/snapd/desktop:/var/lib/snapd/desktop",
    "npm_package_dependencies__mat_datetimepicker_moment": "4.0.1",
    "npm_package_devDependencies_codelyzer": "5.2.1",
    "npm_config_cache_lock_retries": "10",
    "npm_config_searchstaleness": "900",
    "LC_NUMERIC": "pt_BR.UTF-8",
    "npm_package_dependencies_date_fns": "2.9.0",
    "npm_package_devDependencies__angularclass_hmr": "2.1.3",
    "npm_config_save_prefix": "",
    "npm_config_node_options": "",
    "npm_config_scripts_prepend_node_path": "warn-only",
    "LC_PAPER": "pt_BR.UTF-8",
    "npm_config_group": "1001",
    "npm_config_init_author_email": "",
    "npm_config_searchexclude": "",
    "VTE_VERSION": "5802",
    "npm_package_dependencies__mat_datetimepicker_core": "4.0.1",
    "npm_package_dependencies_zone_js": "0.10.3",
    "npm_package_devDependencies__angular_devkit_build_angular": "0.901.0",
    "npm_config_git": "git",
    "npm_config_optional": "true",
    "npm_package_dependencies__angular_platform_browser": "9.1.0",
    "npm_config_json": "",
    "INIT_CWD": "/home/eduardo/PhpStormProjects/supp-core/supp-administrativo-frontend"
  },
  "userLimits": {
    "core_file_size_blocks": {
      "soft": 0,
      "hard": "unlimited"
    },
    "data_seg_size_kbytes": {
      "soft": "unlimited",
      "hard": "unlimited"
    },
    "file_size_blocks": {
      "soft": "unlimited",
      "hard": "unlimited"
    },
    "max_locked_memory_bytes": {
      "soft": 67108864,
      "hard": 67108864
    },
    "max_memory_size_kbytes": {
      "soft": "unlimited",
      "hard": "unlimited"
    },
    "open_files": {
      "soft": 1048576,
      "hard": 1048576
    },
    "stack_size_bytes": {
      "soft": 8388608,
      "hard": "unlimited"
    },
    "cpu_time_seconds": {
      "soft": "unlimited",
      "hard": "unlimited"
    },
    "max_user_processes": {
      "soft": 63238,
      "hard": 63238
    },
    "virtual_memory_kbytes": {
      "soft": "unlimited",
      "hard": "unlimited"
    }
  },
  "sharedObjects": [
    "linux-vdso.so.1",
    "/lib/x86_64-linux-gnu/libdl.so.2",
    "/usr/lib/x86_64-linux-gnu/libstdc++.so.6",
    "/lib/x86_64-linux-gnu/libm.so.6",
    "/lib/x86_64-linux-gnu/libgcc_s.so.1",
    "/lib/x86_64-linux-gnu/libpthread.so.0",
    "/lib/x86_64-linux-gnu/libc.so.6",
    "/lib64/ld-linux-x86-64.so.2"
  ]
}